simpleui_ext/__init__.py
simpleui_ext/apps.py
simpleui_ext/templates/admin/change_list_results.html
simpleui_ext/templates/admin/includes/fieldset.html
simpleui_ext/templates/widgets/select.html
simpleui_ext/templates/widgets/select_opt.html
simpleui_ext-0.1.dist-info/LICENSE
simpleui_ext-0.1.dist-info/METADATA
simpleui_ext-0.1.dist-info/WHEEL
simpleui_ext-0.1.dist-info/top_level.txt
simpleui_ext-0.1.dist-info/RECORD
